flumut/DataClass.py
flumut/DbReader.py
flumut/Exceptions.py
flumut/FluMut.py
flumut/OutputFormatter.py
flumut/Updater.py
flumut/__init__.py
flumut/cli.py
flumut-0.6.4.dist-info/licenses/LICENSE
flumutdata/__init__.py
flumutdata/flumut_output.xlsm
flumut-0.6.4.dist-info/METADATA
flumut-0.6.4.dist-info/WHEEL
flumut-0.6.4.dist-info/entry_points.txt
flumut-0.6.4.dist-info/top_level.txt
flumut-0.6.4.dist-info/RECORD
