Metadata-Version: 2.4
Name: flumut
Version: 0.6.4
Summary: A tool to search for molecular markers with potential impact on the biological characteristics of Influenza A viruses of the A(H5N1) subtype.
Author-email: Edoardo Giussani <egiussani@izsvenezie.it>, Alessandro Sartori <asartori@izsvenezie.it>
License:                     GNU AFFERO GENERAL PUBLIC LICENSE
Project-URL: Home-page, https://github.com/izsvenezie-virology/FluMut
Requires-Python: >=3.7
License-File: LICENSE
Requires-Dist: click>=8.0.0
Requires-Dist: flumutdb>=6.0
Requires-Dist: biopython>=1.81
Requires-Dist: openpyxl>=3.1.2
Requires-Dist: importlib-resources>=1.3
Dynamic: license-file
